gptk/__init__.py
gptk/constants.py
gptk/encoding.py
gptk/enums.py
gptk/pydocument.py
gptk/singletons.py
gptk-0.4.0.dist-info/LICENSE.md
gptk-0.4.0.dist-info/METADATA
gptk-0.4.0.dist-info/WHEEL
gptk-0.4.0.dist-info/top_level.txt
gptk-0.4.0.dist-info/RECORD
